intercept_it/__init__.py
intercept_it/interceptors/__init__.py
intercept_it/interceptors/base_interceptor.py
intercept_it/interceptors/global_interceptor.py
intercept_it/interceptors/looped_interceptor.py
intercept_it/interceptors/nested_interceptor.py
intercept_it/interceptors/unit_interceptor.py
intercept_it/loggers/__init__.py
intercept_it/loggers/base_logger.py
intercept_it/loggers/std_logger.py
intercept_it/utils/__init__.py
intercept_it/utils/checker.py
intercept_it/utils/default_formatters.py
intercept_it/utils/default_handlers.py
intercept_it/utils/enums.py
intercept_it/utils/exceptions.py
intercept_it/utils/models.py
intercept_it-0.1.0.dist-info/LICENSE
intercept_it-0.1.0.dist-info/METADATA
intercept_it-0.1.0.dist-info/WHEEL
intercept_it-0.1.0.dist-info/top_level.txt
intercept_it-0.1.0.dist-info/RECORD
