Metadata-Version: 2.1
Name: intercept-it
Version: 0.1.0
Summary: Customized exceptions handling
Home-page: https://github.com/pro100broo/intercept-it
Author: Simon Shalnev
Author-email: Simon Shalnev <shalnev.sema@mail.ru>
License: MIT
Project-URL: Homepage, https://github.com/pro100broo/intercept-it
Project-URL: Examples, https://github.com/pro100broo/intercept-it/examples
Classifier: Programming Language :: Python :: 3.12
Classifier: Programming Language :: Python :: 3.13
Classifier: Development Status :: 4 - Beta
Classifier: Topic :: Software Development :: Libraries
Classifier: Typing :: Typed
Requires-Python: >=3.12
License-File: LICENSE
Requires-Dist: annotated-types==0.7.0
Requires-Dist: colorama==0.4.6
Requires-Dist: loguru==0.7.2
Requires-Dist: pydantic==2.9.2
Requires-Dist: pydantic_core==2.23.4
Requires-Dist: pytz==2024.2
Requires-Dist: setuptools==75.5.0
Requires-Dist: typing_extensions==4.12.2
Requires-Dist: win32-setctime==1.1.0
